streamwatch/__init__.py
streamwatch/app.py
streamwatch/cache.py
streamwatch/config.py
streamwatch/constants.py
streamwatch/container.py
streamwatch/core.py
streamwatch/database.py
streamwatch/exceptions.py
streamwatch/logging_config.py
streamwatch/main.py
streamwatch/menu_handler.py
streamwatch/migration.py
streamwatch/models.py
streamwatch/naming_standards.py
streamwatch/performance.py
streamwatch/playback_controller.py
streamwatch/player.py
streamwatch/py.typed
streamwatch/rate_limiter.py
streamwatch/recording.py
streamwatch/recording_menu.py
streamwatch/resilience.py
streamwatch/result.py
streamwatch/stream_checker.py
streamwatch/stream_manager.py
streamwatch/stream_utils.py
streamwatch/ui_security.py
streamwatch/validation_utils.py
streamwatch/validators.py
streamwatch/commands/__init__.py
streamwatch/commands/base.py
streamwatch/commands/invoker.py
streamwatch/commands/playback_commands.py
streamwatch/commands/recording_commands.py
streamwatch/commands/stream_commands.py
streamwatch/stubs/__init__.py
streamwatch/stubs/streamlink.pyi
streamwatch/ui/__init__.py
streamwatch/ui/display.py
streamwatch/ui/input_handler.py
streamwatch/ui/pagination.py
streamwatch/ui/styles.py
streamwatch-0.4.3.dist-info/METADATA
streamwatch-0.4.3.dist-info/WHEEL
streamwatch-0.4.3.dist-info/entry_points.txt
streamwatch-0.4.3.dist-info/licenses/LICENSE
streamwatch-0.4.3.dist-info/RECORD
