Metadata-Version: 2.4
Name: streamwatch
Version: 0.4.3
Summary: A CLI tool to manage, check status, and play favorite live streams.
Project-URL: Homepage, https://snowballons.github.io/streamwatch-cli
Project-URL: Documentation, https://github.com/snowballons/streamwatch-cli#readme
Project-URL: Repository, https://github.com/snowballons/streamwatch-cli
Author-email: Johny Snow <snowballons@protonmail.com>
License: MIT License
License-File: LICENSE
Keywords: cli,interactive,live,manager,player,stream,streaming,streamlink,twitch,youtube
Classifier: Development Status :: 4 - Beta
Classifier: Environment :: Console
Classifier: Intended Audience :: End Users/Desktop
Classifier: License :: OSI Approved :: MIT License
Classifier: Operating System :: OS Independent
Classifier: Programming Language :: Python :: 3
Classifier: Programming Language :: Python :: 3.8
Classifier: Programming Language :: Python :: 3.9
Classifier: Programming Language :: Python :: 3.10
Classifier: Programming Language :: Python :: 3.11
Classifier: Programming Language :: Python :: 3.12
Classifier: Topic :: Multimedia :: Video
Classifier: Topic :: Terminals
Classifier: Topic :: Utilities
Requires-Python: >=3.8.1
Requires-Dist: certifi
Requires-Dist: lxml
Requires-Dist: prompt-toolkit>=3.0.0
Requires-Dist: pycryptodome
Requires-Dist: pydantic>=2.0.0
Requires-Dist: requests>=2.25.0
Requires-Dist: rich>=13.9.5
Requires-Dist: streamlink>=6.0.0
Requires-Dist: urllib3>=1.26.0
Requires-Dist: validators>=0.22.0
Requires-Dist: websocket-client
Provides-Extra: dev
Requires-Dist: bandit; extra == 'dev'
Requires-Dist: black; extra == 'dev'
Requires-Dist: flake8; extra == 'dev'
Requires-Dist: isort; extra == 'dev'
Requires-Dist: mypy; extra == 'dev'
Requires-Dist: pre-commit; extra == 'dev'
Requires-Dist: pytest; extra == 'dev'
Requires-Dist: pytest-asyncio; extra == 'dev'
Requires-Dist: pytest-cov; extra == 'dev'
Requires-Dist: pytest-mock; extra == 'dev'
Requires-Dist: twine; extra == 'dev'
Requires-Dist: types-requests; extra == 'dev'
